beancount_hangseng/DBS.py
beancount_hangseng/MPowerMasterCard.py
beancount_hangseng/Savings.py
beancount_hangseng/__init__.py
beancount_hangseng/utils.py
beancount_hangseng/scripts/csv.py
beancount_hangseng-0.4.0.data/scripts/beancount-hangseng-csv
beancount_hangseng-0.4.0.dist-info/LICENSE
beancount_hangseng-0.4.0.dist-info/METADATA
beancount_hangseng-0.4.0.dist-info/WHEEL
beancount_hangseng-0.4.0.dist-info/top_level.txt
beancount_hangseng-0.4.0.dist-info/RECORD
