Metadata-Version: 2.1
Name: beancount-hangseng
Version: 0.4.0
Summary: Parse Hang Seng eStatements to Beancount/CSV
Home-page: https://github.com/yiufung/beancount-hangseng
Author: Cheong Yiu Fung
Author-email: mail@yiufung.net
License: UNKNOWN
Platform: UNKNOWN
Classifier: Programming Language :: Python :: 3
Classifier: Topic :: Office/Business :: Financial :: Accounting
Classifier: Topic :: Office/Business :: Financial :: Spreadsheet
Classifier: License :: OSI Approved :: GNU General Public License v3 (GPLv3)
Classifier: Operating System :: OS Independent
Requires-Dist: beancount
